wexample_wex_addon_dev_python-0.0.63.dist-info/METADATA
wexample_wex_addon_dev_python-0.0.63.dist-info/WHEEL
wexample_wex_addon_dev_python-0.0.63.dist-info/entry_points.txt
wexample_wex_addon_dev_python/__init__.py
wexample_wex_addon_dev_python/__pycache__/__init__.py
wexample_wex_addon_dev_python/commands/__init__.py
wexample_wex_addon_dev_python/commands/code/__init__.py
wexample_wex_addon_dev_python/commands/code/check.py
wexample_wex_addon_dev_python/commands/code/check/__init__.py
wexample_wex_addon_dev_python/commands/code/check/mypy.py
wexample_wex_addon_dev_python/commands/code/check/pylint.py
wexample_wex_addon_dev_python/commands/code/check/pyright.py
wexample_wex_addon_dev_python/commands/code/format.py
wexample_wex_addon_dev_python/commands/code/format/__init__.py
wexample_wex_addon_dev_python/commands/code/format/black.py
wexample_wex_addon_dev_python/commands/code/format/isort.py
wexample_wex_addon_dev_python/commands/examples/__init__.py
wexample_wex_addon_dev_python/commands/examples/utils/__init__.py
wexample_wex_addon_dev_python/commands/examples/utils/some_example_type.py
wexample_wex_addon_dev_python/commands/examples/validate.py
wexample_wex_addon_dev_python/commands/release/__init__.py
wexample_wex_addon_dev_python/config_value/__init__.py
wexample_wex_addon_dev_python/config_value/__pycache__/__init__.py
wexample_wex_addon_dev_python/config_value/python_package_readme_config_value.py
wexample_wex_addon_dev_python/const/__init__.py
wexample_wex_addon_dev_python/const/__pycache__/__init__.py
wexample_wex_addon_dev_python/const/package.py
wexample_wex_addon_dev_python/const/python.py
wexample_wex_addon_dev_python/file/__init__.py
wexample_wex_addon_dev_python/file/__pycache__/__init__.py
wexample_wex_addon_dev_python/file/python_app_iml_file.py
wexample_wex_addon_dev_python/file/python_pyproject_toml_file.py
wexample_wex_addon_dev_python/middleware/__init__.py
wexample_wex_addon_dev_python/middleware/__pycache__/__init__.py
wexample_wex_addon_dev_python/middleware/each_python_file_middleware.py
wexample_wex_addon_dev_python/py.typed
wexample_wex_addon_dev_python/python_addon_manager.py
wexample_wex_addon_dev_python-0.0.63.dist-info/RECORD
